<?xml version="1.0" encoding="UTF-8"?>
<beans xmlns="http://www.springframework.org/schema/beans"
       xmlns:xsi="http://www.w3.org/2001/XMLSchema-instance"
       xmlns:tx="http://www.springframework.org/schema/tx"
       xmlns:aop="http://www.springframework.org/schema/aop"
       xsi:schemaLocation="http://www.springframework.org/schema/beans
       http://www.springframework.org/schema/beans/spring-beans.xsd

       http://www.springframework.org/schema/tx http://www.springframework.org/schema/tx/spring-tx.xsd
       http://www.springframework.org/schema/aop https://www.springframework.org/schema/aop/spring-aop.xsd">

    <!-- (事务管理)transaction manager, use JtaTransactionManager for global tx -->
    <bean id="transactionManager"
          class="org.springframework.jdbc.datasource.DataSourceTransactionManager">
        <property name="dataSource" ref="hikariDataSource"/>
    </bean>

    <!-- 定义事务增强处理 -->
    <tx:advice id="txAdvice" transaction-manager="transactionManager">
        <tx:attributes>
            <!-- read-only="true"属性设置提高事务处理性能 -->
            <tx:method name="find*" read-only="true"/>
            <tx:method name="search*" read-only="true"/>
            <tx:method name="query*" read-only="true"/>
            <tx:method name="select*" read-only="true"/>
            <tx:method name="list*" read-only="true"/>
            <tx:method name="get*" read-only="true"/>

            <!-- propagation 事务传播机制 -->
            <tx:method name="add*" propagation="REQUIRED"/>
            <tx:method name="save*" propagation="REQUIRED"/>
            <tx:method name="insert*" propagation="REQUIRED"/>

            <tx:method name="del*" propagation="REQUIRED"/>
            <tx:method name="delete*" propagation="REQUIRED"/>
            <tx:method name="remove*" propagation="REQUIRED"/>

            <tx:method name="update*" propagation="REQUIRED"/>
            <tx:method name="modify*" propagation="REQUIRED"/>
            <tx:method name="merge*" propagation="REQUIRED"/>

            <tx:method name="do*" propagation="REQUIRED"/>
            <tx:method name="*" propagation="REQUIRED"/>
        </tx:attributes>
    </tx:advice>


    <!-- 定义事务处理切面 -->
    <aop:config>
        <aop:pointcut expression="execution(* com.iogogogo.ssm.service.impl.*.*(..))" id="pointcut"/>
        <!-- 将事务增强与切入点组合 -->
        <aop:advisor advice-ref="txAdvice" pointcut-ref="pointcut"/>
    </aop:config>

</beans>
